{
  "file": "charmos/kernel/elf.c",
  "c_parse": {
    "functions": [
      {
        "name": "elf_load",
        "return_type": "uint64_t",
        "parameters": [
          {
            "type": "void",
            "name": "*elf_data"
          }
        ],
        "qualifiers": [],
        "line": 15
      },
      {
        "name": "elf_map",
        "return_type": "void",
        "parameters": [
          {
            "type": "uintptr_t",
            "name": "user_pml4_phys"
          },
          {
            "type": "void",
            "name": "*elf_data"
          }
        ],
        "qualifiers": [],
        "line": 45
      },
      {
        "name": "map_user_stack",
        "return_type": "uintptr_t",
        "parameters": [
          {
            "type": "uintptr_t",
            "name": "user_pml4_phys"
          }
        ],
        "qualifiers": [],
        "line": 102
      },
      {
        "name": "syscall_setup",
        "return_type": "void",
        "parameters": [
          {
            "type": "void",
            "name": "*syscall_entry"
          }
        ],
        "qualifiers": [],
        "line": 117
      },
      {
        "name": "enter_userspace",
        "return_type": "void",
        "parameters": [
          {
            "type": "uintptr_t",
            "name": "entry_point"
          },
          {
            "type": "uintptr_t",
            "name": "user_stack_top"
          },
          {
            "type": "uint16_t",
            "name": "user_cs"
          },
          {
            "type": "uint16_t",
            "name": "user_ss"
          },
          {
            "type": "uintptr_t",
            "name": "user_pml4_phys"
          }
        ],
        "qualifiers": [],
        "line": 130
      }
    ],
    "types": {
      "structs": [],
      "enums": [],
      "typedefs": []
    }
  },
  "ideas": []
}