{
  "file": "charmos/kernel/drivers/nvme/init.c",
  "c_parse": {
    "functions": [
      {
        "name": "nvme_enable_controller",
        "return_type": "void",
        "parameters": [
          {
            "type": "struct nvme_device",
            "name": "*nvme"
          }
        ],
        "qualifiers": [],
        "line": 17
      },
      {
        "name": "nvme_setup_admin_queues",
        "return_type": "void",
        "parameters": [
          {
            "type": "struct nvme_device",
            "name": "*nvme"
          }
        ],
        "qualifiers": [],
        "line": 50
      },
      {
        "name": "nvme_alloc_admin_queues",
        "return_type": "void",
        "parameters": [
          {
            "type": "struct nvme_device",
            "name": "*nvme"
          }
        ],
        "qualifiers": [],
        "line": 67
      },
      {
        "name": "nvme_alloc_io_queues",
        "return_type": "void",
        "parameters": [
          {
            "type": "struct nvme_device",
            "name": "*nvme"
          },
          {
            "type": "uint32_t",
            "name": "qid"
          }
        ],
        "qualifiers": [],
        "line": 94
      }
    ],
    "types": {
      "structs": [],
      "enums": [],
      "typedefs": []
    }
  },
  "ideas": []
}