{
  "file": "charmos/kernel/sch/resched.c",
  "c_parse": {
    "functions": [
      {
        "name": "scheduler_mark_core_needs_resched",
        "return_type": "bool",
        "parameters": [
          {
            "type": "struct core",
            "name": "*c"
          },
          {
            "type": "bool",
            "name": "new"
          }
        ],
        "qualifiers": [],
        "line": 5
      },
      {
        "name": "scheduler_mark_self_needs_resched",
        "return_type": "bool",
        "parameters": [
          {
            "type": "bool",
            "name": "new"
          }
        ],
        "qualifiers": [],
        "line": 9
      },
      {
        "name": "scheduler_self_needs_resched",
        "return_type": "bool",
        "parameters": [
          {
            "type": "void",
            "name": null
          }
        ],
        "qualifiers": [],
        "line": 13
      },
      {
        "name": "scheduler_resched_if_needed",
        "return_type": "void",
        "parameters": [
          {
            "type": "void",
            "name": null
          }
        ],
        "qualifiers": [],
        "line": 17
      },
      {
        "name": "scheduler_mark_self_idle",
        "return_type": "void",
        "parameters": [
          {
            "type": "bool",
            "name": "new"
          }
        ],
        "qualifiers": [],
        "line": 27
      },
      {
        "name": "scheduler_core_idle",
        "return_type": "bool",
        "parameters": [
          {
            "type": "struct core",
            "name": "*c"
          }
        ],
        "qualifiers": [],
        "line": 32
      },
      {
        "name": "scheduler_force_resched",
        "return_type": "void",
        "parameters": [
          {
            "type": "struct scheduler",
            "name": "*sched"
          }
        ],
        "qualifiers": [],
        "line": 37
      }
    ],
    "types": {
      "structs": [],
      "enums": [],
      "typedefs": []
    }
  },
  "ideas": []
}